leven_clustering-0.0.1.dist-info/METADATA
leven_clustering-0.0.1.dist-info/WHEEL
leven_clustering/__init__.py
leven_clustering/leven_clustering.cpython-36m-x86_64-linux-gnu.so
leven_clustering-0.0.1.dist-info/RECORD
