Metadata-Version: 2.1
Name: leven-clustering
Version: 0.0.1
Summary: Simple hierarchical clustering using levenshtein ratio
Keywords: clustering levenshtein rust
Author: Yaraslau Byshyk <dev@shyk.by>
Author-Email: Yaraslau Byshyk <dev@shyk.by>
